{"title":"去ansys.net去看了看","zzzContent":"<p>去ansys.net去看了看<br />\n这个网站是我以后的目标和对手.感觉:<br />\n1.网站开通应该不久,所以alexa排名在540166,而我的ansys.org.cn在397960,但是日排名上,我的是168717,而ansys.net是122313,这个差别很大了,而ansys.net是英文站,alexa排名没有道理比ansys.org.cn低,唯一的原因就是:他们的开通时间不长,而ansys.org.cn已经差不多3个月了,.<br />\n2.ansys.net的资金实力很不错的,人脉关系也不错,查看alexa的用户记录,用户同时去的网站还有ansys.com,这是ansys的全球官方站点.据说ansys.net的管理员还是ansys的资深工程师,所以&#8230;.ansys.com也可能进行了推荐,所以虽说ansys.net开通不久,google pagerank已经有4(我认为光ansys.com做个链接就足够让他的pagerank达到4了)<br />\n3.ansys.net的规划很有条理,比我的ansys.org.cn好多了,域名也申请的早,我在申请ansys.org.cn的时候他已经把域名抢了.记得那时候我去ansys.net看过,那时候他还没有把ansys.net做起来,只是放了几张照片,页面就写了一段话&#8221;welcome my homepage.you are ***st visitor.&#8221;后面的意思大致是他刚刚买了一个数码相机,所以拍几张图片来放上去,这个网页做的很简陋,是因为dreamweaver太贵了,等过些时候再去买这个软件.(哈哈,老外的软件都比硬件贵阿,我老早用dreamweaver了,只要4块钱就可以买盗版,不过现在还没有一个数码相机).而现在的ansys.net首页也分两大块,一块是ansys的内容,另一块链接到了另外一个网站,是日文的,不知道什么意思,看图片内容似乎是一个介绍日本料理或者用数码相机记载日常生活的网站,应该是日志性质的.这说明主办者主要可能还是出于兴趣和业余爱好而办的这个网站.但是里面的ansys的部分做得相当专业,虽然不怎么漂亮,但是程序后台似乎是基于apache上的(大概也跟iis的系统平台太贵了),apache+cgi的架构,还比较落后了,但是程序架构颇有功底,input file ,marco library,等好几个库整理的很好,从链接看似乎是数据都是存在静态文件上,他的分类是根据?mycat后面的关键词来做的,点击后进去的Inputfile library的文件是****.inp,marco library里面的文章后缀名是.mac,因此可以断定这个网站是独立的服务器(虚拟主机不可能给你自己设定apache里的文件后缀的.)<br />\n4.ansys的有些文档似乎是从哪个论坛整理的,不知道是怎么来的.其分类和宏,命令流也考虑了ansys的版本的因素,用到的ansys的版本也都比较老.</p>\n<p>5.突然看到了ansys.net的更新日志,发现:<br />\n        1 ansys的创建时间是在2000年3月,后来改改停停.<br />\n\t2.这个网站的更新内容似乎来自于一个xansys.org或者其他的什么组织.<br />\n\t4.作者声明这个网站跟ansys公司没有什么联系,不代表ansys公司的官方立场,不对任何内容负责\n</p>","postDate":"2005-06-01 14:14:54","postId":113,"type":"post","status":"publish","imported":true,"file":"113.md"}